[
  {
    "symbol": "AMAT",
    "date": "2024-10-27",
    "stockPrice": 185.34,
    "numberOfShares": 827000000,
    "marketCapitalization": 153276180000,
    "minusCashAndCashEquivalents": 8022000000,
    "addTotalDebt": 6259000000,
    "enterpriseValue": 151513180000
  },
  {
    "symbol": "AMAT",
    "date": "2023-10-29",
    "stockPrice": 131.03,
    "numberOfShares": 840000000,
    "marketCapitalization": 110065200000,
    "minusCashAndCashEquivalents": 6132000000,
    "addTotalDebt": 5999000000,
    "enterpriseValue": 109932200000
  },
  {
    "symbol": "AMAT",
    "date": "2022-10-30",
    "stockPrice": 88.29,
    "numberOfShares": 871000000,
    "marketCapitalization": 76900590000,
    "minusCashAndCashEquivalents": 1995000000,
    "addTotalDebt": 5829000000,
    "enterpriseValue": 80734590000
  },
  {
    "symbol": "AMAT",
    "date": "2021-10-31",
    "stockPrice": 139.51,
    "numberOfShares": 910000000,
    "marketCapitalization": 126954099999,
    "minusCashAndCashEquivalents": 4995000000,
    "addTotalDebt": 5753000000,
    "enterpriseValue": 127712099999
  },
  {
    "symbol": "AMAT",
    "date": "2020-10-25",
    "stockPrice": 59.51,
    "numberOfShares": 916000000,
    "marketCapitalization": 54511160000,
    "minusCashAndCashEquivalents": 5351000000,
    "addTotalDebt": 5707000000,
    "enterpriseValue": 54867160000
  },
  {
    "symbol": "AMAT",
    "date": "2019-10-27",
    "stockPrice": 56.95,
    "numberOfShares": 937000000,
    "marketCapitalization": 53362150000,
    "minusCashAndCashEquivalents": 3129000000,
    "addTotalDebt": 5313000000,
    "enterpriseValue": 55546150000
  },
  {
    "symbol": "AMAT",
    "date": "2018-10-28",
    "stockPrice": 31.12,
    "numberOfShares": 1013000000,
    "marketCapitalization": 31524560000,
    "minusCashAndCashEquivalents": 3440000000,
    "addTotalDebt": 5309000000,
    "enterpriseValue": 33393560000
  },
  {
    "symbol": "AMAT",
    "date": "2017-10-29",
    "stockPrice": 55.9,
    "numberOfShares": 1073000000,
    "marketCapitalization": 59980700000,
    "minusCashAndCashEquivalents": 5010000000,
    "addTotalDebt": 5304000000,
    "enterpriseValue": 60274700000
  },
  {
    "symbol": "AMAT",
    "date": "2016-10-30",
    "stockPrice": 29.08,
    "numberOfShares": 1107000000,
    "marketCapitalization": 32191560000,
    "minusCashAndCashEquivalents": 3406000000,
    "addTotalDebt": 3325000000,
    "enterpriseValue": 32110560000
  },
  {
    "symbol": "AMAT",
    "date": "2015-10-25",
    "stockPrice": 16.33,
    "numberOfShares": 1214000000,
    "marketCapitalization": 19824619999,
    "minusCashAndCashEquivalents": 4797000000,
    "addTotalDebt": 4542000000,
    "enterpriseValue": 19569619999
  },
  {
    "symbol": "AMAT",
    "date": "2014-10-26",
    "stockPrice": 21.04,
    "numberOfShares": 1215000000,
    "marketCapitalization": 25563600000,
    "minusCashAndCashEquivalents": 3002000000,
    "addTotalDebt": 1947000000,
    "enterpriseValue": 24508600000
  },
  {
    "symbol": "AMAT",
    "date": "2013-10-27",
    "stockPrice": 17.73,
    "numberOfShares": 1202000000,
    "marketCapitalization": 21311460000,
    "minusCashAndCashEquivalents": 1711000000,
    "addTotalDebt": 1946000000,
    "enterpriseValue": 21546460000
  },
  {
    "symbol": "AMAT",
    "date": "2012-10-28",
    "stockPrice": 10.65,
    "numberOfShares": 1266000000,
    "marketCapitalization": 13482900000,
    "minusCashAndCashEquivalents": 1392000000,
    "addTotalDebt": 1946000000,
    "enterpriseValue": 14036900000
  },
  {
    "symbol": "AMAT",
    "date": "2011-10-30",
    "stockPrice": 12.32,
    "numberOfShares": 1319000000,
    "marketCapitalization": 16250080000,
    "minusCashAndCashEquivalents": 5960000000,
    "addTotalDebt": 1947000000,
    "enterpriseValue": 12237080000
  },
  {
    "symbol": "AMAT",
    "date": "2010-10-31",
    "stockPrice": 12.37,
    "numberOfShares": 1339949000,
    "marketCapitalization": 16575169129,
    "minusCashAndCashEquivalents": 1857664000,
    "addTotalDebt": 205529000,
    "enterpriseValue": 14923034129
  },
  {
    "symbol": "AMAT",
    "date": "2009-10-25",
    "stockPrice": 12.93,
    "numberOfShares": 1333091000,
    "marketCapitalization": 17236866630,
    "minusCashAndCashEquivalents": 1576381000,
    "addTotalDebt": 201894000,
    "enterpriseValue": 15862379630
  },
  {
    "symbol": "AMAT",
    "date": "2008-10-26",
    "stockPrice": 11.3,
    "numberOfShares": 1354176000,
    "marketCapitalization": 15302188800,
    "minusCashAndCashEquivalents": 1411624000,
    "addTotalDebt": 202644000,
    "enterpriseValue": 14093208800
  },
  {
    "symbol": "AMAT",
    "date": "2007-10-28",
    "stockPrice": 18.97,
    "numberOfShares": 1406685000,
    "marketCapitalization": 26684814450,
    "minusCashAndCashEquivalents": 1202722000,
    "addTotalDebt": 204842000,
    "enterpriseValue": 25686934450
  },
  {
    "symbol": "AMAT",
    "date": "2006-10-29",
    "stockPrice": 17.35,
    "numberOfShares": 1551339000,
    "marketCapitalization": 26915731650,
    "minusCashAndCashEquivalents": 861463000,
    "addTotalDebt": 407243000,
    "enterpriseValue": 26461511650
  },
  {
    "symbol": "AMAT",
    "date": "2005-10-30",
    "stockPrice": 16.36,
    "numberOfShares": 1654740000,
    "marketCapitalization": 27071546400,
    "minusCashAndCashEquivalents": 990342000,
    "addTotalDebt": 414954000,
    "enterpriseValue": 26496158400
  },
  {
    "symbol": "AMAT",
    "date": "2004-10-31",
    "stockPrice": 15.99,
    "numberOfShares": 1688121000,
    "marketCapitalization": 26993054790,
    "minusCashAndCashEquivalents": 1493292000,
    "addTotalDebt": 456300000,
    "enterpriseValue": 25956062790
  },
  {
    "symbol": "AMAT",
    "date": "2003-10-26",
    "stockPrice": 20.72,
    "numberOfShares": 1657189000,
    "marketCapitalization": 34336956080,
    "minusCashAndCashEquivalents": 1364857000,
    "addTotalDebt": 561714000,
    "enterpriseValue": 33533813080
  },
  {
    "symbol": "AMAT",
    "date": "2002-10-27",
    "stockPrice": 15.12,
    "numberOfShares": 1643612000,
    "marketCapitalization": 24851413440,
    "minusCashAndCashEquivalents": 1284791000,
    "addTotalDebt": 623629000,
    "enterpriseValue": 24190251440
  },
  {
    "symbol": "AMAT",
    "date": "2001-10-28",
    "stockPrice": 17.25,
    "numberOfShares": 1626404000,
    "marketCapitalization": 28055469000,
    "minusCashAndCashEquivalents": 1356304000,
    "addTotalDebt": 569612000,
    "enterpriseValue": 27268777000
  },
  {
    "symbol": "AMAT",
    "date": "2000-10-29",
    "stockPrice": 24.81,
    "numberOfShares": 1613160000,
    "marketCapitalization": 40022499600,
    "minusCashAndCashEquivalents": 1647604000,
    "addTotalDebt": 679423000,
    "enterpriseValue": 39054318600
  },
  {
    "symbol": "AMAT",
    "date": "1999-10-31",
    "stockPrice": 21.94,
    "numberOfShares": 1557208000,
    "marketCapitalization": 34165143520,
    "minusCashAndCashEquivalents": 823300000,
    "addTotalDebt": 626700000,
    "enterpriseValue": 33968543520
  },
  {
    "symbol": "AMAT",
    "date": "1998-10-25",
    "stockPrice": 8.33,
    "numberOfShares": 1467396000,
    "marketCapitalization": 12223408680,
    "minusCashAndCashEquivalents": 575200000,
    "addTotalDebt": 624600000,
    "enterpriseValue": 12272808680
  },
  {
    "symbol": "AMAT",
    "date": "1997-10-26",
    "stockPrice": 7.63,
    "numberOfShares": 3022704000,
    "marketCapitalization": 23063231520,
    "minusCashAndCashEquivalents": 448000000,
    "addTotalDebt": 689600000,
    "enterpriseValue": 23304831520
  },
  {
    "symbol": "AMAT",
    "date": "1996-10-27",
    "stockPrice": 3.28,
    "numberOfShares": 1427619000,
    "marketCapitalization": 4682590320,
    "minusCashAndCashEquivalents": 403900000,
    "addTotalDebt": 375600000,
    "enterpriseValue": 4654290320
  },
  {
    "symbol": "AMAT",
    "date": "1995-10-29",
    "stockPrice": 6.38,
    "numberOfShares": 2837568000,
    "marketCapitalization": 18103683840,
    "minusCashAndCashEquivalents": 285800000,
    "addTotalDebt": 362600000,
    "enterpriseValue": 18180483840
  },
  {
    "symbol": "AMAT",
    "date": "1994-10-30",
    "stockPrice": 3.25,
    "numberOfShares": 1360336000,
    "marketCapitalization": 4421092000,
    "minusCashAndCashEquivalents": 160300000,
    "addTotalDebt": 267600000,
    "enterpriseValue": 4528392000
  },
  {
    "symbol": "AMAT",
    "date": "1993-10-31",
    "stockPrice": 2.13,
    "numberOfShares": 1246250000,
    "marketCapitalization": 2654512500,
    "minusCashAndCashEquivalents": 119600000,
    "addTotalDebt": 169800000,
    "enterpriseValue": 2704712500
  },
  {
    "symbol": "AMAT",
    "date": "1992-10-31",
    "stockPrice": 0.92188,
    "numberOfShares": 1128571000,
    "marketCapitalization": 1040407033,
    "minusCashAndCashEquivalents": 159500000,
    "addTotalDebt": 152300000,
    "enterpriseValue": 1033207033
  },
  {
    "symbol": "AMAT",
    "date": "1991-10-31",
    "stockPrice": 0.37891,
    "numberOfShares": 1048000000,
    "marketCapitalization": 397097680,
    "minusCashAndCashEquivalents": 125200000,
    "addTotalDebt": 160700000,
    "enterpriseValue": 432597680
  },
  {
    "symbol": "AMAT",
    "date": "1990-10-31",
    "stockPrice": 0.27344,
    "numberOfShares": 974286000,
    "marketCapitalization": 266408763,
    "minusCashAndCashEquivalents": 57100000,
    "addTotalDebt": 81000000,
    "enterpriseValue": 290308763
  },
  {
    "symbol": "AMAT",
    "date": "1989-10-31",
    "stockPrice": 0.39844,
    "numberOfShares": 1030000000,
    "marketCapitalization": 410393200,
    "minusCashAndCashEquivalents": 57400000,
    "addTotalDebt": 43700000,
    "enterpriseValue": 396693200
  },
  {
    "symbol": "AMAT",
    "date": "1988-10-31",
    "stockPrice": 0.34766,
    "numberOfShares": 1000000000,
    "marketCapitalization": 347660000,
    "minusCashAndCashEquivalents": 100800000,
    "addTotalDebt": 21800000,
    "enterpriseValue": 268660000
  },
  {
    "symbol": "AMAT",
    "date": "1987-10-31",
    "stockPrice": 0.24219,
    "numberOfShares": 990272000,
    "marketCapitalization": 239833975,
    "minusCashAndCashEquivalents": 70700000,
    "addTotalDebt": 25800000,
    "enterpriseValue": 194933975
  },
  {
    "symbol": "AMAT",
    "date": "1986-10-31",
    "stockPrice": 0.16016,
    "numberOfShares": 840448000,
    "marketCapitalization": 134606151,
    "minusCashAndCashEquivalents": 21800000,
    "addTotalDebt": 28300000,
    "enterpriseValue": 141106151
  },
  {
    "symbol": "AMAT",
    "date": "1985-10-31",
    "stockPrice": 0.15625,
    "numberOfShares": 620000000,
    "marketCapitalization": 96875000,
    "minusCashAndCashEquivalents": 35700000,
    "addTotalDebt": 26900000,
    "enterpriseValue": 88075000
  }
]