{
  "symbol": "AMBR",
  "historical": [
    {
      "date": "2025-04-07",
      "open": 9.99,
      "high": 10.6,
      "low": 8.72,
      "close": 10.24,
      "adjClose": 10.24,
      "volume": 60100,
      "unadjustedVolume": 60100,
      "change": 0.25,
      "changePercent": 2.5,
      "vwap": 9.89,
      "label": "April 07, 25",
      "changeOverTime": 0.025
    },
    {
      "date": "2025-04-04",
      "open": 10.25,
      "high": 10.35,
      "low": 9.66,
      "close": 9.99,
      "adjClose": 9.99,
      "volume": 103400,
      "unadjustedVolume": 103400,
      "change": -0.26,
      "changePercent": -2.54,
      "vwap": 10.06,
      "label": "April 04, 25",
      "changeOverTime": -0.0254
    },
    {
      "date": "2025-04-03",
      "open": 11,
      "high": 11.15,
      "low": 10.23,
      "close": 10.23,
      "adjClose": 10.23,
      "volume": 31926,
      "unadjustedVolume": 31926,
      "change": -0.77,
      "changePercent": -7,
      "vwap": 10.65,
      "label": "April 03, 25",
      "changeOverTime": -0.07
    },
    {
      "date": "2025-04-02",
      "open": 11.1,
      "high": 11.59,
      "low": 10.6,
      "close": 11.29,
      "adjClose": 11.29,
      "volume": 27922,
      "unadjustedVolume": 27922,
      "change": 0.19,
      "changePercent": 1.71,
      "vwap": 11.15,
      "label": "April 02, 25",
      "changeOverTime": 0.0171
    },
    {
      "date": "2025-04-01",
      "open": 11.9,
      "high": 11.95,
      "low": 10.13,
      "close": 11.38,
      "adjClose": 11.38,
      "volume": 362900,
      "unadjustedVolume": 362900,
      "change": -0.52,
      "changePercent": -4.37,
      "vwap": 11.34,
      "label": "April 01, 25",
      "changeOverTime": -0.0437
    },
    {
      "date": "2025-03-31",
      "open": 11.65,
      "high": 12,
      "low": 11.37,
      "close": 11.98,
      "adjClose": 11.98,
      "volume": 44800,
      "unadjustedVolume": 44800,
      "change": 0.33,
      "changePercent": 2.83,
      "vwap": 11.75,
      "label": "March 31, 25",
      "changeOverTime": 0.0283
    },
    {
      "date": "2025-03-28",
      "open": 11.52,
      "high": 12.6,
      "low": 11.52,
      "close": 12.04,
      "adjClose": 12.04,
      "volume": 95900,
      "unadjustedVolume": 95900,
      "change": 0.52,
      "changePercent": 4.51,
      "vwap": 11.92,
      "label": "March 28, 25",
      "changeOverTime": 0.0451
    },
    {
      "date": "2025-03-27",
      "open": 12.18,
      "high": 12.5,
      "low": 11.63,
      "close": 12.05,
      "adjClose": 12.05,
      "volume": 86000,
      "unadjustedVolume": 86000,
      "change": -0.13,
      "changePercent": -1.07,
      "vwap": 12.09,
      "label": "March 27, 25",
      "changeOverTime": -0.0107
    },
    {
      "date": "2025-03-26",
      "open": 12.18,
      "high": 12.33,
      "low": 11.85,
      "close": 12.02,
      "adjClose": 12.02,
      "volume": 75014,
      "unadjustedVolume": 75014,
      "change": -0.16,
      "changePercent": -1.31,
      "vwap": 12.1,
      "label": "March 26, 25",
      "changeOverTime": -0.0131
    },
    {
      "date": "2025-03-25",
      "open": 11.8,
      "high": 12.3,
      "low": 11.51,
      "close": 12.1,
      "adjClose": 12.1,
      "volume": 129438,
      "unadjustedVolume": 129438,
      "change": 0.3,
      "changePercent": 2.54,
      "vwap": 11.93,
      "label": "March 25, 25",
      "changeOverTime": 0.0254
    },
    {
      "date": "2025-03-24",
      "open": 12.06,
      "high": 12.7,
      "low": 11.78,
      "close": 12.25,
      "adjClose": 12.25,
      "volume": 108400,
      "unadjustedVolume": 108400,
      "change": 0.19,
      "changePercent": 1.58,
      "vwap": 12.2,
      "label": "March 24, 25",
      "changeOverTime": 0.0158
    },
    {
      "date": "2025-03-21",
      "open": 11.6,
      "high": 12.55,
      "low": 11.5,
      "close": 12.07,
      "adjClose": 12.07,
      "volume": 81240,
      "unadjustedVolume": 81240,
      "change": 0.47,
      "changePercent": 4.05,
      "vwap": 11.93,
      "label": "March 21, 25",
      "changeOverTime": 0.0405
    },
    {
      "date": "2025-03-20",
      "open": 12,
      "high": 12.52,
      "low": 11.6,
      "close": 11.6,
      "adjClose": 11.6,
      "volume": 71700,
      "unadjustedVolume": 71700,
      "change": -0.4,
      "changePercent": -3.33,
      "vwap": 11.93,
      "label": "March 20, 25",
      "changeOverTime": -0.0333
    },
    {
      "date": "2025-03-19",
      "open": 11.72,
      "high": 12.62,
      "low": 11.2,
      "close": 12.31,
      "adjClose": 12.31,
      "volume": 83900,
      "unadjustedVolume": 83900,
      "change": 0.59,
      "changePercent": 5.03,
      "vwap": 11.96,
      "label": "March 19, 25",
      "changeOverTime": 0.0503
    },
    {
      "date": "2025-03-18",
      "open": 12.34,
      "high": 12.5,
      "low": 11.23,
      "close": 11.81,
      "adjClose": 11.81,
      "volume": 186300,
      "unadjustedVolume": 186300,
      "change": -0.53,
      "changePercent": -4.29,
      "vwap": 11.97,
      "label": "March 18, 25",
      "changeOverTime": -0.0429
    },
    {
      "date": "2025-03-17",
      "open": 12.33,
      "high": 13.09,
      "low": 12.05,
      "close": 12.79,
      "adjClose": 12.79,
      "volume": 293122,
      "unadjustedVolume": 293122,
      "change": 0.46,
      "changePercent": 3.73,
      "vwap": 12.57,
      "label": "March 17, 25",
      "changeOverTime": 0.0373
    },
    {
      "date": "2025-03-14",
      "open": 11.5,
      "high": 11.99,
      "low": 10.34,
      "close": 11.88,
      "adjClose": 11.88,
      "volume": 241700,
      "unadjustedVolume": 241700,
      "change": 0.38,
      "changePercent": 3.3,
      "vwap": 11.43,
      "label": "March 14, 25",
      "changeOverTime": 0.033
    },
    {
      "date": "2025-03-13",
      "open": 9.31,
      "high": 11.25,
      "low": 9.31,
      "close": 11,
      "adjClose": 11,
      "volume": 289700,
      "unadjustedVolume": 289700,
      "change": 1.69,
      "changePercent": 18.15,
      "vwap": 10.22,
      "label": "March 13, 25",
      "changeOverTime": 0.1815
    },
    {
      "date": "2025-03-12",
      "open": 8.85,
      "high": 9.97,
      "low": 8.78,
      "close": 9.24,
      "adjClose": 9.24,
      "volume": 148000,
      "unadjustedVolume": 148000,
      "change": 0.39,
      "changePercent": 4.41,
      "vwap": 9.21,
      "label": "March 12, 25",
      "changeOverTime": 0.0441
    },
    {
      "date": "2025-03-11",
      "open": 8.1,
      "high": 8.68,
      "low": 8.1,
      "close": 8.4,
      "adjClose": 8.4,
      "volume": 64500,
      "unadjustedVolume": 64500,
      "change": 0.3,
      "changePercent": 3.7,
      "vwap": 8.32,
      "label": "March 11, 25",
      "changeOverTime": 0.037
    },
    {
      "date": "2025-03-10",
      "open": 7.82,
      "high": 8.24,
      "low": 7.56,
      "close": 7.99,
      "adjClose": 7.99,
      "volume": 65200,
      "unadjustedVolume": 65200,
      "change": 0.17,
      "changePercent": 2.17,
      "vwap": 7.9,
      "label": "March 10, 25",
      "changeOverTime": 0.0217
    },
    {
      "date": "2025-03-07",
      "open": 7.44,
      "high": 8.13,
      "low": 7.44,
      "close": 7.81,
      "adjClose": 7.81,
      "volume": 48000,
      "unadjustedVolume": 48000,
      "change": 0.37,
      "changePercent": 4.97,
      "vwap": 7.71,
      "label": "March 07, 25",
      "changeOverTime": 0.0497
    }
  ]
}