[
  {
    "symbol": "AMPFX",
    "date": "2024-01-31",
    "stockPrice": 38.21,
    "numberOfShares": 17560518,
    "marketCapitalization": 670987392,
    "minusCashAndCashEquivalents": 223397000,
    "addTotalDebt": 8378000,
    "enterpriseValue": 455968392
  },
  {
    "symbol": "AMPFX",
    "date": "2023-01-31",
    "stockPrice": 32.32,
    "numberOfShares": 17641401,
    "marketCapitalization": 570170080,
    "minusCashAndCashEquivalents": 69612000,
    "addTotalDebt": 9855000,
    "enterpriseValue": 510413080
  },
  {
    "symbol": "AMPFX",
    "date": "2022-01-31",
    "stockPrice": 40.18,
    "numberOfShares": 17951698,
    "marketCapitalization": 721299225,
    "minusCashAndCashEquivalents": 229846000,
    "addTotalDebt": 6390000,
    "enterpriseValue": 497843225
  },
  {
    "symbol": "AMPFX",
    "date": "2021-01-31",
    "stockPrice": 39.17,
    "numberOfShares": 18502115,
    "marketCapitalization": 724727844,
    "minusCashAndCashEquivalents": 144501000,
    "addTotalDebt": 7439000,
    "enterpriseValue": 587665844
  },
  {
    "symbol": "AMPFX",
    "date": "2020-01-31",
    "stockPrice": 33.08,
    "numberOfShares": 18954076,
    "marketCapitalization": 627000834,
    "minusCashAndCashEquivalents": 179658000,
    "addTotalDebt": 10688000,
    "enterpriseValue": 458030834
  },
  {
    "symbol": "AMPFX",
    "date": "2019-01-31",
    "stockPrice": 29.86,
    "numberOfShares": 19320000,
    "marketCapitalization": 576895200,
    "minusCashAndCashEquivalents": 188531000,
    "addTotalDebt": 0,
    "enterpriseValue": 388364200
  },
  {
    "symbol": "AMPFX",
    "date": "2018-01-31",
    "stockPrice": 33.46,
    "numberOfShares": 19788000,
    "marketCapitalization": 662106480,
    "minusCashAndCashEquivalents": 190988000,
    "addTotalDebt": 0,
    "enterpriseValue": 471118480
  },
  {
    "symbol": "AMPFX",
    "date": "2017-01-31",
    "stockPrice": 27.91,
    "numberOfShares": 19761000,
    "marketCapitalization": 551529510,
    "minusCashAndCashEquivalents": 188576000,
    "addTotalDebt": 0,
    "enterpriseValue": 362953510
  },
  {
    "symbol": "AMPFX",
    "date": "2016-01-31",
    "stockPrice": 24.21,
    "numberOfShares": 21921000,
    "marketCapitalization": 530707410,
    "minusCashAndCashEquivalents": 135765000,
    "addTotalDebt": 0,
    "enterpriseValue": 394942410
  },
  {
    "symbol": "AMPFX",
    "date": "2015-01-31",
    "stockPrice": 27.37,
    "numberOfShares": 24352713,
    "marketCapitalization": 666533754,
    "minusCashAndCashEquivalents": 137697000,
    "addTotalDebt": 0,
    "enterpriseValue": 528836754
  },
  {
    "symbol": "AMPFX",
    "date": "2014-01-31",
    "stockPrice": 26.8,
    "numberOfShares": 24523689,
    "marketCapitalization": 657234865,
    "minusCashAndCashEquivalents": 105149000,
    "addTotalDebt": 0,
    "enterpriseValue": 552085865
  },
  {
    "symbol": "AMPFX",
    "date": "2013-01-31",
    "stockPrice": 22.75,
    "numberOfShares": 24816000,
    "marketCapitalization": 564564000,
    "minusCashAndCashEquivalents": 69073000,
    "addTotalDebt": 0,
    "enterpriseValue": 495491000
  }
]